pydirectchannel/__init__.py
pydirectchannel/directchannel.py
python_directchannel-0.3.6.dist-info/METADATA
python_directchannel-0.3.6.dist-info/WHEEL
python_directchannel-0.3.6.dist-info/top_level.txt
python_directchannel-0.3.6.dist-info/RECORD
