Metadata-Version: 2.1
Name: python-directchannel
Version: 0.3.6
Summary: DirectChannel Mentor API Client
Home-page: https://bitbucket.org/metadonors/python-directchannel
Author: Metadonors
Author-email: fabrizio.arzeni@metadonors.it
License: MIT
Platform: UNKNOWN
Requires-Dist: requests
